Metadata-Version: 2.1
Name: xml-utils
Version: 1.23.0
Summary: XML utils for the curator core project
Home-page: https://github.com/usnistgov/xml_utils
Author: NIST IT Lab
Author-email: itl_inquiries@nist.gov
Provides-Extra: Xerces
License-File: LICENSE.md
